odoo/addons/account_receipt_journal/README.rst
odoo/addons/account_receipt_journal/__init__.py
odoo/addons/account_receipt_journal/__manifest__.py
odoo/addons/account_receipt_journal/data/account_journal_data.xml
odoo/addons/account_receipt_journal/i18n/account_receipt_journal.pot
odoo/addons/account_receipt_journal/i18n/es.po
odoo/addons/account_receipt_journal/i18n/it.po
odoo/addons/account_receipt_journal/models/__init__.py
odoo/addons/account_receipt_journal/models/account_journal.py
odoo/addons/account_receipt_journal/models/account_move.py
odoo/addons/account_receipt_journal/readme/CONTRIBUTORS.rst
odoo/addons/account_receipt_journal/readme/DESCRIPTION.rst
odoo/addons/account_receipt_journal/readme/HISTORY.rst
odoo/addons/account_receipt_journal/static/description/icon.png
odoo/addons/account_receipt_journal/static/description/index.html
odoo/addons/account_receipt_journal/tests/__init__.py
odoo/addons/account_receipt_journal/tests/test_receipts.py
odoo/addons/account_receipt_journal/views/account_journal_views.xml
odoo14_addon_account_receipt_journal-14.0.1.0.1.dev8.dist-info/METADATA
odoo14_addon_account_receipt_journal-14.0.1.0.1.dev8.dist-info/WHEEL
odoo14_addon_account_receipt_journal-14.0.1.0.1.dev8.dist-info/top_level.txt
odoo14_addon_account_receipt_journal-14.0.1.0.1.dev8.dist-info/RECORD
